{
    "articles": [
        {
          "id": "1113",
          "article": "0001",
          "title": "Top 5 cheat codes to use weight on the cut", 
          "author": "Jeevi M",
          "data": "12/15/2024",
          "content": "so first you need to blah blah blah, and then blah blah blah, also a gf man"
        },
        {
          "id": "1112",
          "article": "0002",
          "title": "Top 10 tips and tricks to NOT get arrested when approaching women!", 
          "author": "Alex L",
          "data": "12/14/2024",
          "content": "be rich, successful, AND bench 225 blah, blah blah blah"
        }
    ]
}